{"type": "FeatureCollection", "name": "点", "features": [{"type": "Feature", "properties": {"name": "昆山市", "QUHUADAIMA": "320583", "Location": 6, "Alignment": 1}, "geometry": {"type": "Point", "coordinates": [120.95796334768768, 31.381478092885963]}}, {"type": "Feature", "properties": {"name": "太仓市", "QUHUADAIMA": "320585", "Location": 2, "Alignment": 2}, "geometry": {"type": "Point", "coordinates": [121.10664035312702, 31.44656711552335]}}, {"type": "Feature", "properties": {"name": "常熟市", "QUHUADAIMA": "320581", "Location": 6, "Alignment": 1}, "geometry": {"type": "Point", "coordinates": [120.74547930435561, 31.642179540348057]}}, {"type": "Feature", "properties": {"name": "张家港市", "QUHUADAIMA": "320582", "Location": 6, "Alignment": 1}, "geometry": {"type": "Point", "coordinates": [120.546180222723, 31.866251840115538]}}, {"type": "Feature", "properties": {"name": "虎丘区", "QUHUADAIMA": "320505", "Location": 4, "Alignment": 3}, "geometry": {"type": "Point", "coordinates": [120.5733209931761, 31.29660101102319]}}, {"type": "Feature", "properties": {"name": "吴中区", "QUHUADAIMA": "320506", "Location": 6, "Alignment": 1}, "geometry": {"type": "Point", "coordinates": [120.6322076678559, 31.264473442182698]}}, {"type": "Feature", "properties": {"name": "相城区", "QUHUADAIMA": "320507", "Location": 1, "Alignment": 1}, "geometry": {"type": "Point", "coordinates": [120.62323687199914, 31.363736189373668]}}, {"type": "Feature", "properties": {"name": "姑苏区", "QUHUADAIMA": "320508", "Location": 7, "Alignment": 1}, "geometry": {"type": "Point", "coordinates": [120.61758893479535, 31.336924768769606]}}, {"type": "Feature", "properties": {"name": "吴江区", "QUHUADAIMA": "320509", "Location": 6, "Alignment": 1}, "geometry": {"type": "Point", "coordinates": [120.64440367737879, 31.142881712116026]}}]}