{"type": "FeatureCollection", "name": "点", "features": [{"type": "Feature", "properties": {"name": "四会市", "QUHUADAIMA": "441284", "Location": 6, "Alignment": 1}, "geometry": {"type": "Point", "coordinates": [112.72884696047488, 23.327572298544037]}}, {"type": "Feature", "properties": {"name": "德庆县", "QUHUADAIMA": "441226", "Location": 2, "Alignment": 2}, "geometry": {"type": "Point", "coordinates": [111.77317897706841, 23.14231170462127]}}, {"type": "Feature", "properties": {"name": "广宁县", "QUHUADAIMA": "441223", "Location": 6, "Alignment": 1}, "geometry": {"type": "Point", "coordinates": [112.43758027365145, 23.635154695651458]}}, {"type": "Feature", "properties": {"name": "封开县", "QUHUADAIMA": "441225", "Location": 6, "Alignment": 1}, "geometry": {"type": "Point", "coordinates": [111.50328132087246, 23.438003139009112]}}, {"type": "Feature", "properties": {"name": "怀集县", "QUHUADAIMA": "441224", "Location": 6, "Alignment": 1}, "geometry": {"type": "Point", "coordinates": [112.18503403053163, 23.917381217797164]}}, {"type": "Feature", "properties": {"name": "鼎湖区", "QUHUADAIMA": "441203", "Location": 6, "Alignment": 1}, "geometry": {"type": "Point", "coordinates": [112.56697139915083, 23.17225942133709]}}, {"type": "Feature", "properties": {"name": "端州区", "QUHUADAIMA": "441202", "Location": 2, "Alignment": 2}, "geometry": {"type": "Point", "coordinates": [112.48539647657277, 23.05206169319149]}}, {"type": "Feature", "properties": {"name": "高要区", "QUHUADAIMA": "441283", "Location": 8, "Alignment": 2}, "geometry": {"type": "Point", "coordinates": [112.45718314634317, 23.024275384473793]}}]}