{"type": "FeatureCollection", "name": "点", "features": [{"type": "Feature", "properties": {"name": "松滋市", "QUHUADAIMA": "421087", "Location": 6, "Alignment": 1}, "geometry": {"type": "Point", "coordinates": [111.78198679601441, 30.176446235915144]}}, {"type": "Feature", "properties": {"name": "石首市", "QUHUADAIMA": "421081", "Location": 6, "Alignment": 1}, "geometry": {"type": "Point", "coordinates": [112.40908906451551, 29.7315318185297]}}, {"type": "Feature", "properties": {"name": "洪湖市", "QUHUADAIMA": "421083", "Location": 4, "Alignment": 3}, "geometry": {"type": "Point", "coordinates": [113.47197686540143, 29.813832136652085]}}, {"type": "Feature", "properties": {"name": "江陵县", "QUHUADAIMA": "421024", "Location": 6, "Alignment": 1}, "geometry": {"type": "Point", "coordinates": [112.41446734500072, 30.029606407360152]}}, {"type": "Feature", "properties": {"name": "公安县", "QUHUADAIMA": "421022", "Location": 4, "Alignment": 3}, "geometry": {"type": "Point", "coordinates": [112.23060768912254, 30.06025595853775]}}, {"type": "Feature", "properties": {"name": "监利县", "QUHUADAIMA": "421023", "Location": 6, "Alignment": 1}, "geometry": {"type": "Point", "coordinates": [112.8955518877635, 29.818443279362576]}}, {"type": "Feature", "properties": {"name": "荆州区", "QUHUADAIMA": "421003", "Location": 4, "Alignment": 3}, "geometry": {"type": "Point", "coordinates": [112.190198604905, 30.355750254292076]}}, {"type": "Feature", "properties": {"name": "沙市区", "QUHUADAIMA": "421002", "Location": 6, "Alignment": 1}, "geometry": {"type": "Point", "coordinates": [112.25403038679296, 30.314125390016756]}}]}