{"type": "FeatureCollection", "name": "点", "features": [{"type": "Feature", "properties": {"name": "集贤县", "QUHUADAIMA": "230521", "Location": 2, "Alignment": 2}, "geometry": {"type": "Point", "coordinates": [131.1363556590409, 46.72211573825832]}}, {"type": "Feature", "properties": {"name": "友谊县", "QUHUADAIMA": "230522", "Location": 6, "Alignment": 1}, "geometry": {"type": "Point", "coordinates": [131.80578999535072, 46.775625026197744]}}, {"type": "Feature", "properties": {"name": "宝清县", "QUHUADAIMA": "230523", "Location": 6, "Alignment": 1}, "geometry": {"type": "Point", "coordinates": [132.21164407697074, 46.325900744697506]}}, {"type": "Feature", "properties": {"name": "饶河县", "QUHUADAIMA": "230524", "Location": 4, "Alignment": 3}, "geometry": {"type": "Point", "coordinates": [134.02266028538105, 46.79765806052501]}}, {"type": "Feature", "properties": {"name": "尖山区", "QUHUADAIMA": "230502", "Location": 4, "Alignment": 3}, "geometry": {"type": "Point", "coordinates": [131.1531759737151, 46.63769314608406]}}, {"type": "Feature", "properties": {"name": "四方台区", "QUHUADAIMA": "230505", "Location": 2, "Alignment": 2}, "geometry": {"type": "Point", "coordinates": [131.33390320823344, 46.5904444533504]}}, {"type": "Feature", "properties": {"name": "宝山区", "QUHUADAIMA": "230506", "Location": 8, "Alignment": 2}, "geometry": {"type": "Point", "coordinates": [131.40744777004417, 46.571388716014454]}}, {"type": "Feature", "properties": {"name": "岭东区", "QUHUADAIMA": "230503", "Location": 8, "Alignment": 2}, "geometry": {"type": "Point", "coordinates": [131.14023742581676, 46.567725333983546]}}]}