{"type": "FeatureCollection", "name": "点", "features": [{"type": "Feature", "properties": {"name": "洪江市", "QUHUADAIMA": "431281", "Location": 6, "Alignment": 1}, "geometry": {"type": "Point", "coordinates": [109.8487366515338, 27.211350632538466]}}, {"type": "Feature", "properties": {"name": "辰溪县", "QUHUADAIMA": "431223", "Location": 6, "Alignment": 1}, "geometry": {"type": "Point", "coordinates": [110.1880366204536, 28.00716057594017]}}, {"type": "Feature", "properties": {"name": "沅陵县", "QUHUADAIMA": "431222", "Location": 4, "Alignment": 3}, "geometry": {"type": "Point", "coordinates": [110.4019774425506, 28.452873318397913]}}, {"type": "Feature", "properties": {"name": "芷江侗族自治县", "QUHUADAIMA": "431228", "Location": 2, "Alignment": 2}, "geometry": {"type": "Point", "coordinates": [109.68926020664767, 27.441179662981614]}}, {"type": "Feature", "properties": {"name": "溆浦县", "QUHUADAIMA": "431224", "Location": 6, "Alignment": 1}, "geometry": {"type": "Point", "coordinates": [110.59460436307711, 27.913325537707898]}}, {"type": "Feature", "properties": {"name": "麻阳苗族自治县", "QUHUADAIMA": "431226", "Location": 8, "Alignment": 2}, "geometry": {"type": "Point", "coordinates": [109.80616327514078, 27.8572176092651]}}, {"type": "Feature", "properties": {"name": "中方县", "QUHUADAIMA": "431221", "Location": 5, "Alignment": 6}, "geometry": {"type": "Point", "coordinates": [109.94367853770544, 27.441184649793286]}}, {"type": "Feature", "properties": {"name": "新晃侗族自治县", "QUHUADAIMA": "431227", "Location": 6, "Alignment": 1}, "geometry": {"type": "Point", "coordinates": [109.17378056856118, 27.358556093852712]}}, {"type": "Feature", "properties": {"name": "通道侗族自治县", "QUHUADAIMA": "431230", "Location": 3, "Alignment": 3}, "geometry": {"type": "Point", "coordinates": [109.78437810007064, 26.15875458808714]}}, {"type": "Feature", "properties": {"name": "靖州苗族侗族自治县", "QUHUADAIMA": "431229", "Location": 8, "Alignment": 2}, "geometry": {"type": "Point", "coordinates": [109.69520747821153, 26.578040851448087]}}, {"type": "Feature", "properties": {"name": "会同县", "QUHUADAIMA": "431225", "Location": 6, "Alignment": 1}, "geometry": {"type": "Point", "coordinates": [109.72163089037687, 26.8729867229252]}}, {"type": "Feature", "properties": {"name": "鹤城区", "QUHUADAIMA": "431202", "Location": 2, "Alignment": 2}, "geometry": {"type": "Point", "coordinates": [109.96203588357064, 27.5505732733776]}}]}