{"type": "FeatureCollection", "name": "点", "features": [{"type": "Feature", "properties": {"name": "翔安区", "QUHUADAIMA": "350213", "Location": 6, "Alignment": 1}, "geometry": {"type": "Point", "coordinates": [118.24321512619363, 24.60758430695388]}}, {"type": "Feature", "properties": {"name": "湖里区", "QUHUADAIMA": "350206", "Location": 3, "Alignment": 1}, "geometry": {"type": "Point", "coordinates": [118.09332614826252, 24.505928352479515]}}, {"type": "Feature", "properties": {"name": "思明区", "QUHUADAIMA": "350203", "Location": 6, "Alignment": 1}, "geometry": {"type": "Point", "coordinates": [118.08268865719035, 24.44782857920189]}}, {"type": "Feature", "properties": {"name": "同安区", "QUHUADAIMA": "350212", "Location": 6, "Alignment": 1}, "geometry": {"type": "Point", "coordinates": [118.151782693987, 24.726162567241346]}}, {"type": "Feature", "properties": {"name": "集美区", "QUHUADAIMA": "350211", "Location": 2, "Alignment": 4}, "geometry": {"type": "Point", "coordinates": [118.1007203289734, 24.56900422951495]}}, {"type": "Feature", "properties": {"name": "海沧区", "QUHUADAIMA": "350205", "Location": 6, "Alignment": 1}, "geometry": {"type": "Point", "coordinates": [117.98437978653473, 24.460335637509512]}}]}